yorn/__init__.py
yorn/__main__.py
yorn/ask.py
yorn-0.0.6.dist-info/METADATA
yorn-0.0.6.dist-info/RECORD
yorn-0.0.6.dist-info/WHEEL
yorn-0.0.6.dist-info/entry_points.txt
yorn-0.0.6.dist-info/top_level.txt
