Metadata-Version: 2.1
Name: yorn
Version: 0.0.6
Summary: A boringly simple CLI input function.
Home-page: https://github.com/tslight/yorn
Author: Toby Slight
Author-email: tobyslight@gmail.com
License: UNKNOWN
Platform: UNKNOWN
Classifier: Programming Language :: Python :: 3
Classifier: License :: OSI Approved :: ISC License (ISCL)
Classifier: Operating System :: OS Independent
